ndsLogFetcher/setup.py
ndsLogFetcher-1.1.dist-info/METADATA
ndsLogFetcher-1.1.dist-info/RECORD
ndsLogFetcher-1.1.dist-info/WHEEL
ndsLogFetcher-1.1.dist-info/top_level.txt
