Metadata-Version: 2.1
Name: ndsLogFetcher
Version: 1.1
Summary: Log Fetcher
Home-page: http://github.com/ckoksal/ndsLogFetcher
Author: Cagri Koksal
Author-email: koksal.cagri@gmail.com
License: none
Platform: UNKNOWN
Requires-Python: >=3
Requires-Dist: paramiko
